qsentry/__init__.py
qsentry/api.py
qsentry/commands.py
qsentry/qsentry.py
qsentry/click/__init__.py
qsentry/click/get.py
qsentry/click/main.py
qsentry/click/update.py
qsentry/click/utils.py
qsentry-0.0.36.dist-info/LICENSE
qsentry-0.0.36.dist-info/METADATA
qsentry-0.0.36.dist-info/WHEEL
qsentry-0.0.36.dist-info/entry_points.txt
qsentry-0.0.36.dist-info/top_level.txt
qsentry-0.0.36.dist-info/RECORD
