Metadata-Version: 2.1
Name: qsentry
Version: 0.0.36
Summary: A command wrapper for Sentry API
Home-page: https://github.com/bqbn/qsentry
Author: bqbn
Author-email: bqbn@openken.com
Project-URL: Bug Reports, https://github.com/bqbn/qsentry/issues
Project-URL: Source, https://github.com/bqbn/qsentry
Keywords: devops utility utils
Classifier: Development Status :: 4 - Beta
Classifier: Intended Audience :: Developers
Classifier: Intended Audience :: System Administrators
Classifier: Topic :: Software Development :: Build Tools
Classifier: Programming Language :: Python :: 3
Requires-Python: <4,>=3
License-File: LICENSE
Requires-Dist: click (~=8.1)
Requires-Dist: jmespath (~=1.0)
Requires-Dist: python-dotenv (~=0.20)
Requires-Dist: requests (~=2.27)
Provides-Extra: dev
Requires-Dist: black (~=22.3) ; extra == 'dev'
Requires-Dist: build (~=0.7.0) ; extra == 'dev'
Requires-Dist: pipenv-setup (~=3.2) ; extra == 'dev'
Requires-Dist: twine (~=4.0) ; extra == 'dev'
Requires-Dist: wheel (~=0.37) ; extra == 'dev'
